modules/trigger/edge_detector.v

/*
    Edge detector module

    This module detects when the input signal crosses a determinated value.
    It can be configured to detect positive and negative edges.
    The output is a single bit that becames one during one clock each time the
    crossing condition is met.

    Note #1:
    This module only detects the crossing. The logic involving the selection of
    the source of trigger belongs outside this module.

    Note #2:
    The current implementation (0.1) has a delay of 1 (ONE) sample, meaning that
    a crossing detection corresponds to a previous sample.

    IMPORTANT:
    Since at the moment (2017/07/19) the controlled enviroment for testbench is
    not developed, this was NOT TESTED!

    Authors:
                AD      Andres Demski
                AK      Ariel Kukulanski
                IP      Ivan Paunovic
                NC      Nahuel Carducci

    Version:
                Date            Number          Name            Modified by     Comment
                2017/07/19      0.1             Crossing        AK              First version. UNTESTED!

    ToDo:
                Date            Suggested by    Priority    Activity                Description
                2017/07/19      AK              High        TEST                    Make testbench!
                2017/07/19      AK              Low         Add complexity          Filter, avoid false detections due to noise

    Releases:   In development ...

*/
`timescale 1ns/1ps
module edge_detector  (
    input       clk,                // clock
    input       rst,                // asynchronous reset
    input [7:0] trigger_value,      // trigger value
    input [7:0] input_sample,       // input samples of the trigger source
    input       in_ena,             // sample available for read
    output      triggered=0         // trigger detected (delays ONE clock)
);
    parameter CLOCK_PERIOD_NS = 10;

    // Finite State Machine
    reg [1:0] state;            // State register
    localparam  searching=0,    // First condition not met: waiting for signal to be under (over) trigger value, when searching for positive (negative) edge
                validating=1;   // First contition met: signal under (over) trigger value, when searching for positive (negative) edge

     always @(posedge clk or posedge rst) begin
        triggered <= 1'b0;
        if (rst)
            state <= searching;
        else begin
            case (state)

                searching:
                    if(input_sample < trigger_value) state <= validating;

                validating:
                    if(input_sample >= trigger_value) begin
                        state <= searching;
                        triggered <= 1'b1;
                    end

                default:
                    state <= searching;
            endcase
        end
    end

    `ifdef COCOTB_SIM
    initial begin
      $dumpfile ("waveform.vcd");
      $dumpvars (0,edge_detector);
      #1;
    end
    `endif

endmodule

modules/trigger/test_edge_detector/waveform.vcd
$date
	Sat Jul 22 16:44:41 2017
$end
$version
	Icarus Verilog
$end
$timescale
	1ps
$end
$scope module edge_detector $end
$var wire 1 ! clk $end
$var wire 1 " in_ena $end
$var wire 8 # input_sample [7:0] $end
$var wire 1 $ rst $end
$var wire 8 % trigger_value [7:0] $end
$var reg 2 & state [1:0] $end
$var reg 1 ' triggered $end
$upscope $end
$enddefinitions $end
#0
$dumpvars
0'
b0 &
b110010 %
0$
b0 #
0"
1!
$end
#5000
0!
#10000
b1 &
1!
#15000
0!
#20000
1!
#25000
0!
#30000
1!
#35000
0!
#40000
1!
#45000
0!
#50000
1!
#55000
0!
#60000
1!
#65000
0!
#70000
1!
#75000
0!
#80000
1!
#85000
0!
#90000
b0 &
1$
1!
#95000
0!
#100000
0$
1!
#105000
0!
#110000
1"
b10000000 #
b1 &
1!
#115000
0!
#120000
0"
1'
b0 &
1!
#125000
0!
#130000
0'
1!
#135000
0!
#140000
1!
#145000
0!
#150000
1"
b10011000 #
1!
#155000
0!
#160000
0"
1!
#165000
0!
#170000
1!
#175000
0!
#180000
1!
#185000
0!
#190000
1"
b10110000 #
1!
#195000
0!
#200000
0"
1!
#205000
0!
#210000
1!
#215000
0!
#220000
1!
#225000
0!
#230000
1"
b11000100 #
1!
#235000
0!
#240000
0"
1!
#245000
0!
#250000
1!
#255000
0!
#260000
1!
#265000
0!
#270000
1"
b11010100 #
1!
#275000
0!
#280000
0"
1!
#285000
0!
#290000
1!
#295000
0!
#300000
1!
#305000
0!
#310000
1"
b11011111 #
1!
#315000
0!
#320000
0"
1!
#325000
0!
#330000
1!
#335000
0!
#340000
1!
#345000
0!
#350000
1"
b11100011 #
1!
#355000
0!
#360000
0"
1!
#365000
0!
#370000
1!
#375000
0!
#380000
1!
#385000
0!
#390000
1"
b11100010 #
1!
#395000
0!
#400000
0"
1!
#405000
0!
#410000
1!
#415000
0!
#420000
1!
#425000
0!
#430000
1"
b11011010 #
1!
#435000
0!
#440000
0"
1!
#445000
0!
#450000
1!
#455000
0!
#460000
1!
#465000
0!
#470000
1"
b11001101 #
1!
#475000
0!
#480000
0"
1!
#485000
0!
#490000
1!
#495000
0!
#500000
1!
#505000
0!
#510000
1"
b10111010 #
1!
#515000
0!
#520000
0"
1!
#525000
0!
#530000
1!
#535000
0!
#540000
1!
#545000
0!
#550000
1"
b10100100 #
1!
#555000
0!
#560000
0"
1!
#565000
0!
#570000
1!
#575000
0!
#580000
1!
#585000
0!
#590000
1"
b10001100 #
1!
#595000
0!
#600000
0"
1!
#605000
0!
#610000
1!
#615000
0!
#620000
1!
#625000
0!
#630000
1"
b1110011 #
1!
#635000
0!
#640000
0"
1!
#645000
0!
#650000
1!
#655000
0!
#660000
1!
#665000
0!
#670000
1"
b1011011 #
1!
#675000
0!
#680000
0"
1!
#685000
0!
#690000
1!
#695000
0!
#700000
1!
#705000
0!
#710000
1"
b1000101 #
1!
#715000
0!
#720000
0"
1!
#725000
0!
#730000
1!
#735000
0!
#740000
1!
#745000
0!
#750000
1"
b110010 #
1!
#755000
0!
#760000
0"
1!
#765000
0!
#770000
1!
#775000
0!
#780000
1!
#785000
0!
#790000
1"
b100101 #
1!
#795000
0!
#800000
0"
b1 &
1!
#805000
0!
#810000
1!
#815000
0!
#820000
1!
#825000
0!
#830000
1"
b11101 #
1!
#835000
0!
#840000
0"
1!
#845000
0!
#850000
1!
#855000
0!
#860000
1!
#865000
0!
#870000
1"
b11100 #
1!
#875000
0!
#880000
0"
1!
#885000
0!
#890000
1!
#895000
0!
#900000
1!
#905000
0!
#910000
1"
b100000 #
1!
#915000
0!
#920000
0"
1!
#925000
0!
#930000
1!
#935000
0!
#940000
1!
#945000
0!
#950000
1"
b101011 #
1!
#955000
0!
#960000
0"
1!
#965000
0!
#970000
1!
#975000
0!
#980000
1!
#985000
0!
#990000
1"
b111011 #
1!
#995000
0!
#1000000
0"
1'
b0 &
1!
#1005000
0!
#1010000
0'
1!
#1015000
0!
#1020000
1!
#1025000
0!
#1030000
1"
b1001111 #
1!
#1035000
0!
#1040000
0"
1!
#1045000
0!
#1050000
1!
#1055000
0!
#1060000
1!
#1065000
0!
#1070000
1"
b1100111 #
1!
#1075000
0!
#1080000
0"
1!
#1085000
0!
#1090000
1!
#1095000
0!
#1100000
1!
#1105000
0!
#1110000
1"
b10000000 #
1!
#1115000
0!
#1120000
0"
1!
#1125000
0!
#1130000
1!
#1135000
0!
#1140000
1!
#1145000
0!
#1150000
1"
b10011000 #
1!
#1155000
0!
#1160000
0"
1!
#1165000
0!
#1170000
1!
#1175000
0!
#1180000
1!
#1185000
0!
#1190000
1"
b10110000 #
1!
#1195000
0!
#1200000
0"
1!
#1205000
0!
#1210000
1!
#1215000
0!
#1220000
1!
#1225000
0!
#1230000
1"
b11000100 #
1!
#1235000
0!
#1240000
0"
1!
#1245000
0!
#1250000
1!
#1255000
0!
#1260000
1!
#1265000
0!
#1270000
1"
b11010100 #
1!
#1275000
0!
#1280000
0"
1!
#1285000
0!
#1290000
1!
#1295000
0!
#1300000
1!
#1305000
0!
#1310000
1"
b11011111 #
1!
#1315000
0!
#1320000
0"
1!
#1325000
0!
#1330000
1!
#1335000
0!
#1340000
1!
#1345000
0!
#1350000
1"
b11100011 #
1!
#1355000
0!
#1360000
0"
1!
#1365000
0!
#1370000
1!
#1375000
0!
#1380000
1!
#1385000
0!
#1390000
1"
b11100010 #
1!
#1395000
0!
#1400000
0"
1!
#1405000
0!
#1410000
1!
#1415000
0!
#1420000
1!
#1425000
0!
#1430000
1"
b11011010 #
1!
#1435000
0!
#1440000
0"
1!
#1445000
0!
#1450000
1!
#1455000
0!
#1460000
1!
#1465000
0!
#1470000
1"
b11001101 #
1!
#1475000
0!
#1480000
0"
1!
#1485000
0!
#1490000
1!
#1495000
0!
#1500000
1!
#1505000
0!
#1510000
1"
b10111010 #
1!
#1515000
0!
#1520000
0"
1!
#1525000
0!
#1530000
1!
#1535000
0!
#1540000
1!
#1545000
0!
#1550000
1"
b10100100 #
1!
#1555000
0!
#1560000
0"
1!
#1565000
0!
#1570000
1!
#1575000
0!
#1580000
1!
#1585000
0!
#1590000
1"
b10001100 #
1!
#1595000
0!
#1600000
0"
1!
#1605000
0!
#1610000
1!
#1615000
0!
#1620000
1!
#1625000
0!
#1630000
1"
b1110011 #
1!
#1635000
0!
#1640000
0"
1!
#1645000
0!
#1650000
1!
#1655000
0!
#1660000
1!
#1665000
0!
#1670000
1"
b1011011 #
1!
#1675000
0!
#1680000
0"
1!
#1685000
0!
#1690000
1!
#1695000
0!
#1700000
1!
#1705000
0!
#1710000
1"
b1000101 #
1!
#1715000
0!
#1720000
0"
1!
#1725000
0!
#1730000
1!
#1735000
0!
#1740000
1!
#1745000
0!
#1750000
1"
b110010 #
1!
#1755000
0!
#1760000
0"
1!
#1765000
0!
#1770000
1!
#1775000
0!
#1780000
1!
#1785000
0!
#1790000
1"
b100101 #
1!
#1795000
0!
#1800000
0"
b1 &
1!
#1805000
0!
#1810000
1!
#1815000
0!
#1820000
1!
#1825000
0!
#1830000
1"
b11101 #
1!
#1835000
0!
#1840000
0"
1!
#1845000
0!
#1850000
1!
#1855000
0!
#1860000
1!
#1865000
0!
#1870000
1"
b11100 #
1!
#1875000
0!
#1880000
0"
1!
#1885000
0!
#1890000
1!
#1895000
0!
#1900000
1!
#1905000
0!
#1910000
1"
b100000 #
1!
#1915000
0!
#1920000
0"
1!
#1925000
0!
#1930000
1!
#1935000
0!
#1940000
1!
#1945000
0!
#1950000
1"
b101011 #
1!
#1955000
0!
#1960000
0"
1!
#1965000
0!
#1970000
1!
#1975000
0!
#1980000
1!
#1985000
0!
#1990000
1"
b111011 #
1!
#1995000
0!
#2000000
0"
1'
b0 &
1!
#2005000
0!
#2010000
0'
1!
#2015000
0!
#2020000
1!
#2025000
0!
#2030000
1"
b1001111 #
1!
#2035000
0!
#2040000
0"
1!
#2045000
0!
#2050000
1!
#2055000
0!
#2060000
1!
#2065000
0!
#2070000
1"
b1100111 #
1!
#2075000
0!
#2080000
0"
1!
